synchive/__init__.py
synchive/backup.py
synchive/cli.py
synchive/config.py
synchive-0.5.1.dist-info/METADATA
synchive-0.5.1.dist-info/WHEEL
synchive-0.5.1.dist-info/entry_points.txt
synchive-0.5.1.dist-info/top_level.txt
synchive-0.5.1.dist-info/RECORD
