Metadata-Version: 2.1
Name: synchive
Version: 0.5.1
Summary: Automated file backup and synchronization over SSH within a shared network for seamless data management.
Home-page: UNKNOWN
Author: Harsh Mistry
Author-email: hmistry864@gmail.com
License: UNKNOWN
Platform: UNKNOWN
Requires-Dist: paramiko
Requires-Dist: setuptools
Requires-Dist: twine
Requires-Dist: watchdog
Requires-Dist: wheel
